acuvity/__init__.py
acuvity/_hooks/__init__.py
acuvity/_hooks/registration.py
acuvity/_hooks/sdkhooks.py
acuvity/_hooks/types.py
acuvity/_version.py
acuvity/apex.py
acuvity/apexdiscovery.py
acuvity/apexextend.py
acuvity/basesdk.py
acuvity/guard/__init__.py
acuvity/guard/config.py
acuvity/guard/constants.py
acuvity/guard/errors.py
acuvity/guard/threshold.py
acuvity/httpclient.py
acuvity/models/__init__.py
acuvity/models/alertevent.py
acuvity/models/analyzer.py
acuvity/models/analyzermodel.py
acuvity/models/apierror.py
acuvity/models/detector.py
acuvity/models/elementalerror.py
acuvity/models/extraction.py
acuvity/models/extractionrequest.py
acuvity/models/extractionsummary.py
acuvity/models/latency.py
acuvity/models/mcpmessage.py
acuvity/models/mcpserver.py
acuvity/models/mcptoolannotations.py
acuvity/models/modality.py
acuvity/models/principal.py
acuvity/models/principalapp.py
acuvity/models/principalappuser.py
acuvity/models/principaluser.py
acuvity/models/scanrequest.py
acuvity/models/scanresponse.py
acuvity/models/security.py
acuvity/models/textualdetection.py
acuvity/models/tool.py
acuvity/models/toolchoice.py
acuvity/models/toolresult.py
acuvity/models/tooluse.py
acuvity/models/traceref.py
acuvity/py.typed
acuvity/response/__init__.py
acuvity/response/helper.py
acuvity/response/match.py
acuvity/response/processor.py
acuvity/response/result.py
acuvity/sdk.py
acuvity/sdk.pyi
acuvity/sdkconfiguration.py
acuvity/sdkextend.py
acuvity/types/__init__.py
acuvity/types/basemodel.py
acuvity/utils/__init__.py
acuvity/utils/annotations.py
acuvity/utils/enums.py
acuvity/utils/eventstreaming.py
acuvity/utils/forms.py
acuvity/utils/headers.py
acuvity/utils/logger.py
acuvity/utils/metadata.py
acuvity/utils/queryparams.py
acuvity/utils/requestbodies.py
acuvity/utils/retries.py
acuvity/utils/security.py
acuvity/utils/serializers.py
acuvity/utils/url.py
acuvity/utils/values.py
acuvity-0.7.0.dist-info/LICENSE
acuvity-0.7.0.dist-info/METADATA
acuvity-0.7.0.dist-info/WHEEL
acuvity-0.7.0.dist-info/RECORD
