Metadata-Version: 2.3
Name: acuvity
Version: 0.7.0
Summary: Acuvity Python SDK
Author: Acuvity, Inc.
Requires-Python: >=3.9
Classifier: Programming Language :: Python :: 3
Classifier: Programming Language :: Python :: 3.9
Classifier: Programming Language :: Python :: 3.10
Classifier: Programming Language :: Python :: 3.11
Classifier: Programming Language :: Python :: 3.12
Classifier: Programming Language :: Python :: 3.13
Requires-Dist: PyYAML (>=6.0.2,<7.0.0)
Requires-Dist: eval-type-backport (>=0.2.0)
Requires-Dist: httpx (>=0.28.1)
Requires-Dist: pydantic (>=2.10.3)
Requires-Dist: pyjwt (>=2.9.0,<3.0.0)
Requires-Dist: python-dateutil (>=2.8.2)
Requires-Dist: typing-inspection (>=0.4.0)
Project-URL: Documentation, https://github.com/acuvity/acuvity-python
Project-URL: Homepage, https://acuvity.ai/
